sap/__init__.py
sap/audit_logging/__init__.py
sap/audit_logging/audit_logger.py
sap/audit_logging/loggers.py
sap/audit_logging/plans.py
sap/audit_logging/util.py
sap/audit_logging/messages/__init__.py
sap/audit_logging/messages/audit_message.py
sap/audit_logging/messages/configuration_change_message.py
sap/audit_logging/messages/data_access_message.py
sap/audit_logging/messages/data_modification_message.py
sap/audit_logging/messages/security_event_message.py
sap/audit_logging/messages/transactional_message.py
sap_audit_logging-1.3.1.data/data/version.txt
sap_audit_logging-1.3.1.dist-info/LICENSE
sap_audit_logging-1.3.1.dist-info/METADATA
sap_audit_logging-1.3.1.dist-info/WHEEL
sap_audit_logging-1.3.1.dist-info/top_level.txt
sap_audit_logging-1.3.1.dist-info/RECORD
