Metadata-Version: 2.1
Name: sap-audit-logging
Version: 1.3.1
Summary: SAP Python audit log service client
Home-page: https://www.sap.com/
Author: SAP SE
License: SAP DEVELOPER LICENSE AGREEMENT
Keywords: SAP audit auditlog
Classifier: Programming Language :: Python :: 3.7
Classifier: Programming Language :: Python :: 3.8
Classifier: Programming Language :: Python :: 3.9
Classifier: Programming Language :: Python :: 3.10
Classifier: Programming Language :: Python :: 3.11
Classifier: Development Status :: 5 - Production/Stable
Classifier: Intended Audience :: Developers
Classifier: Operating System :: Microsoft
Classifier: Operating System :: Other OS
Classifier: Topic :: Software Development
Classifier: Topic :: Software Development :: Libraries :: Python Modules
Requires-Python: >=3.7
License-File: LICENSE
Requires-Dist: requests (<3.0,>=2.31.0)
Requires-Dist: cfenv (<1.0,>=0.5.3)
